{"_ts": 1761073851.4902499, "data": [{"symbol": "EIGENUSDT", "sumOpenInterest": "24475598.00000000", "sumOpenInterestValue": "27574002.37750886", "CMCCirculatingSupply": "387378852.23236150", "timestamp": 1760968800000}, {"symbol": "EIGENUSDT", "sumOpenInterest": "25118214.20000000", "sumOpenInterestValue": "28835709.90160000", "CMCCirculatingSupply": "387378852.23236150", "timestamp": 1760972400000}, {"symbol": "EIGENUSDT", "sumOpenInterest": "25444880.00000000", "sumOpenInterestValue": "28615157.08868080", "CMCCirculatingSupply": "387378852.23236150", "timestamp": 1760976000000}, {"symbol": "EIGENUSDT", "sumOpenInterest": "25221568.60000000", "sumOpenInterestValue": "27936672.98194686", "CMCCirculatingSupply": "387378852.23236150", "timestamp": 1760979600000}, {"symbol": "EIGENUSDT", "sumOpenInterest": "25583572.80000000", "sumOpenInterestValue": "28187980.51104000", "CMCCirculatingSupply": "387378852.23236150", "timestamp": 1760983200000}, {"symbol": "EIGENUSDT", "sumOpenInterest": "25673626.40000000", "sumOpenInterestValue": "28356188.14207438", "CMCCirculatingSupply": "387378852.23236150", "timestamp": 1760986800000}, {"symbol": "EIGENUSDT", "sumOpenInterest": "25869438.30000000", "sumOpenInterestValue": "28704728.73768000", "CMCCirculatingSupply": "387378852.23236150", "timestamp": 1760990400000}, {"symbol": "EIGENUSDT", "sumOpenInterest": "25705911.20000000", "sumOpenInterestValue": "28592685.02776000", "CMCCirculatingSupply": "387378852.23236150", "timestamp": 1760994000000}, {"symbol": "EIGENUSDT", "sumOpenInterest": "25992243.00000000", "sumOpenInterestValue": "29340043.89840000", "CMCCirculatingSupply": "387378852.23236150", "timestamp": 1760997600000}, {"symbol": "EIGENUSDT", "sumOpenInterest": "25701199.60000000", "sumOpenInterestValue": "29393895.01405682", "CMCCirculatingSupply": "387378852.23236150", "timestamp": 1761001200000}, {"symbol": "EIGENUSDT", "sumOpenInterest": "25580960.00000000", "sumOpenInterestValue": "29443684.96000000", "CMCCirculatingSupply": "387378852.23236150", "timestamp": 1761004800000}, {"symbol": "EIGENUSDT", "sumOpenInterest": "25415363.60000000", "sumOpenInterestValue": "28945266.34397315", "CMCCirculatingSupply": "387378852.23236150", "timestamp": 1761008400000}, {"symbol": "EIGENUSDT", "sumOpenInterest": "25316048.10000000", "sumOpenInterestValue": "28385517.16161164", "CMCCirculatingSupply": "387378852.23236150", "timestamp": 1761012000000}, {"symbol": "EIGENUSDT", "sumOpenInterest": "25072495.10000000", "sumOpenInterestValue": "27813564.68190378", "CMCCirculatingSupply": "387378852.23236150", "timestamp": 1761015600000}, {"symbol": "EIGENUSDT", "sumOpenInterest": "25191953.80000000", "sumOpenInterestValue": "27535063.46900691", "CMCCirculatingSupply": "387378852.23236150", "timestamp": 1761019200000}, {"symbol": "EIGENUSDT", "sumOpenInterest": "24859764.80000000", "sumOpenInterestValue": "26104310.50426472", "CMCCirculatingSupply": "387378852.23236150", "timestamp": 1761022800000}, {"symbol": "EIGENUSDT", "sumOpenInterest": "25178041.10000000", "sumOpenInterestValue": "26386587.07280000", "CMCCirculatingSupply": "387378852.23236150", "timestamp": 1761026400000}, {"symbol": "EIGENUSDT", "sumOpenInterest": "25281027.70000000", "sumOpenInterestValue": "26647784.52408264", "CMCCirculatingSupply": "387378852.23236150", "timestamp": 1761030000000}, {"symbol": "EIGENUSDT", "sumOpenInterest": "25335799.20000000", "sumOpenInterestValue": "26702213.57618227", "CMCCirculatingSupply": "387378852.23236150", "timestamp": 1761033600000}, {"symbol": "EIGENUSDT", "sumOpenInterest": "25265771.90000000", "sumOpenInterestValue": "26468422.64244000", "CMCCirculatingSupply": "387378852.23236150", "timestamp": 1761037200000}, {"symbol": "EIGENUSDT", "sumOpenInterest": "25257418.90000000", "sumOpenInterestValue": "26394983.24350170", "CMCCirculatingSupply": "387378852.23236150", "timestamp": 1761040800000}, {"symbol": "EIGENUSDT", "sumOpenInterest": "25391476.40000000", "sumOpenInterestValue": "26775311.86380000", "CMCCirculatingSupply": "387378852.23236150", "timestamp": 1761044400000}, {"symbol": "EIGENUSDT", "sumOpenInterest": "25608363.20000000", "sumOpenInterestValue": "27260215.55928171", "CMCCirculatingSupply": "387378852.23236150", "timestamp": 1761048000000}, {"symbol": "EIGENUSDT", "sumOpenInterest": "25419943.00000000", "sumOpenInterestValue": "27306102.77060000", "CMCCirculatingSupply": "387378852.23236150", "timestamp": 1761051600000}, {"symbol": "EIGENUSDT", "sumOpenInterest": "25273792.90000000", "sumOpenInterestValue": "27227162.14600686", "CMCCirculatingSupply": "387378852.23236150", "timestamp": 1761055200000}, {"symbol": "EIGENUSDT", "sumOpenInterest": "24660027.60000000", "sumOpenInterestValue": "28268401.20656448", "CMCCirculatingSupply": "387378852.23236150", "timestamp": 1761058800000}, {"symbol": "EIGENUSDT", "sumOpenInterest": "24260997.90000000", "sumOpenInterestValue": "28301029.76383017", "CMCCirculatingSupply": "387378852.23236150", "timestamp": 1761062400000}, {"symbol": "EIGENUSDT", "sumOpenInterest": "23603157.50000000", "sumOpenInterestValue": "27589730.80175000", "CMCCirculatingSupply": "387378852.23236150", "timestamp": 1761066000000}, {"symbol": "EIGENUSDT", "sumOpenInterest": "23545613.60000000", "sumOpenInterestValue": "27633132.12096000", "CMCCirculatingSupply": "387378852.23236150", "timestamp": 1761069600000}, {"symbol": "EIGENUSDT", "sumOpenInterest": "23688994.70000000", "sumOpenInterestValue": "27884856.71800895", "CMCCirculatingSupply": "387378852.23236150", "timestamp": 1761073200000}]}