{"_ts": 1761085314.5870285, "data": [{"symbol": "LUNA2USDT", "sumOpenInterest": "17629081.00000000", "sumOpenInterestValue": "1729060.26448000", "CMCCirculatingSupply": "709984438.91686000", "timestamp": 1760979600000}, {"symbol": "LUNA2USDT", "sumOpenInterest": "17482186.00000000", "sumOpenInterestValue": "1716750.66520000", "CMCCirculatingSupply": "709984438.91686000", "timestamp": 1760983200000}, {"symbol": "LUNA2USDT", "sumOpenInterest": "17390131.00000000", "sumOpenInterestValue": "1712927.90350000", "CMCCirculatingSupply": "709984438.91686000", "timestamp": 1760986800000}, {"symbol": "LUNA2USDT", "sumOpenInterest": "17296832.00000000", "sumOpenInterestValue": "1714326.03474048", "CMCCirculatingSupply": "709984438.91686000", "timestamp": 1760990400000}, {"symbol": "LUNA2USDT", "sumOpenInterest": "17387047.00000000", "sumOpenInterestValue": "1723915.45169227", "CMCCirculatingSupply": "709984438.91686000", "timestamp": 1760994000000}, {"symbol": "LUNA2USDT", "sumOpenInterest": "17290228.00000000", "sumOpenInterestValue": "1711732.57200000", "CMCCirculatingSupply": "709984438.91686000", "timestamp": 1760997600000}, {"symbol": "LUNA2USDT", "sumOpenInterest": "17320258.00000000", "sumOpenInterestValue": "1710275.53961134", "CMCCirculatingSupply": "709984438.91686000", "timestamp": 1761001200000}, {"symbol": "LUNA2USDT", "sumOpenInterest": "17421025.00000000", "sumOpenInterestValue": "1714228.86000000", "CMCCirculatingSupply": "709984438.91686000", "timestamp": 1761004800000}, {"symbol": "LUNA2USDT", "sumOpenInterest": "17448418.00000000", "sumOpenInterestValue": "1719125.10016234", "CMCCirculatingSupply": "709984438.91686000", "timestamp": 1761008400000}, {"symbol": "LUNA2USDT", "sumOpenInterest": "17372242.00000000", "sumOpenInterestValue": "1700215.93914498", "CMCCirculatingSupply": "709984438.91686000", "timestamp": 1761012000000}, {"symbol": "LUNA2USDT", "sumOpenInterest": "17473424.00000000", "sumOpenInterestValue": "1702318.27891072", "CMCCirculatingSupply": "709984438.91686000", "timestamp": 1761015600000}, {"symbol": "LUNA2USDT", "sumOpenInterest": "17427511.00000000", "sumOpenInterestValue": "1690468.56700000", "CMCCirculatingSupply": "709984438.91686000", "timestamp": 1761019200000}, {"symbol": "LUNA2USDT", "sumOpenInterest": "17081469.00000000", "sumOpenInterestValue": "1639224.36828783", "CMCCirculatingSupply": "709984438.91686000", "timestamp": 1761022800000}, {"symbol": "LUNA2USDT", "sumOpenInterest": "17323622.00000000", "sumOpenInterestValue": "1672595.70410000", "CMCCirculatingSupply": "709984438.91686000", "timestamp": 1761026400000}, {"symbol": "LUNA2USDT", "sumOpenInterest": "16635543.00000000", "sumOpenInterestValue": "1610320.56240000", "CMCCirculatingSupply": "709984438.91686000", "timestamp": 1761030000000}, {"symbol": "LUNA2USDT", "sumOpenInterest": "16567659.00000000", "sumOpenInterestValue": "1615740.56575443", "CMCCirculatingSupply": "709984438.91686000", "timestamp": 1761033600000}, {"symbol": "LUNA2USDT", "sumOpenInterest": "16621532.00000000", "sumOpenInterestValue": "1617275.06360000", "CMCCirculatingSupply": "709984438.91686000", "timestamp": 1761037200000}, {"symbol": "LUNA2USDT", "sumOpenInterest": "16765282.00000000", "sumOpenInterestValue": "1629585.41040000", "CMCCirculatingSupply": "709984438.91686000", "timestamp": 1761040800000}, {"symbol": "LUNA2USDT", "sumOpenInterest": "16726412.00000000", "sumOpenInterestValue": "1639188.37600000", "CMCCirculatingSupply": "709984438.91686000", "timestamp": 1761044400000}, {"symbol": "LUNA2USDT", "sumOpenInterest": "16878710.00000000", "sumOpenInterestValue": "1660462.00040520", "CMCCirculatingSupply": "709984438.91686000", "timestamp": 1761048000000}, {"symbol": "LUNA2USDT", "sumOpenInterest": "16801948.00000000", "sumOpenInterestValue": "1655823.74244548", "CMCCirculatingSupply": "709984438.91686000", "timestamp": 1761051600000}, {"symbol": "LUNA2USDT", "sumOpenInterest": "23010484.00000000", "sumOpenInterestValue": "2461935.63318444", "CMCCirculatingSupply": "709984438.91686000", "timestamp": 1761055200000}, {"symbol": "LUNA2USDT", "sumOpenInterest": "23348077.00000000", "sumOpenInterestValue": "2433365.77003625", "CMCCirculatingSupply": "709984438.91686000", "timestamp": 1761058800000}, {"symbol": "LUNA2USDT", "sumOpenInterest": "22002498.00000000", "sumOpenInterestValue": "2317118.70842676", "CMCCirculatingSupply": "709984438.91686000", "timestamp": 1761062400000}, {"symbol": "LUNA2USDT", "sumOpenInterest": "21454759.00000000", "sumOpenInterestValue": "2248458.74320000", "CMCCirculatingSupply": "709984438.91686000", "timestamp": 1761066000000}, {"symbol": "LUNA2USDT", "sumOpenInterest": "21451742.00000000", "sumOpenInterestValue": "2237416.69060000", "CMCCirculatingSupply": "709984438.91686000", "timestamp": 1761069600000}, {"symbol": "LUNA2USDT", "sumOpenInterest": "21341714.00000000", "sumOpenInterestValue": "2215973.12267630", "CMCCirculatingSupply": "709984438.91686000", "timestamp": 1761073200000}, {"symbol": "LUNA2USDT", "sumOpenInterest": "21085235.00000000", "sumOpenInterestValue": "2178129.86692965", "CMCCirculatingSupply": "709984438.91686000", "timestamp": 1761076800000}, {"symbol": "LUNA2USDT", "sumOpenInterest": "20488517.00000000", "sumOpenInterestValue": "2087779.88230000", "CMCCirculatingSupply": "709984438.91686000", "timestamp": 1761080400000}, {"symbol": "LUNA2USDT", "sumOpenInterest": "20002926.00000000", "sumOpenInterestValue": "2043447.11258166", "CMCCirculatingSupply": "709984438.91686000", "timestamp": 1761084000000}]}