{
  "timestamp": "2025-11-10T22:06:07.190131+08:00",
  "scan_info": {
    "total_symbols": 19,
    "signals_found": 10,
    "filtered": 9
  },
  "signals": [
    {
      "symbol": "BTCUSDT",
      "side": "long",
      "weighted_score": 30,
      "edge": 0.301,
      "confidence": 30,
      "prime_strength": 58,
      "P_chosen": 0.708
    },
    {
      "symbol": "TRUMPUSDT",
      "side": "long",
      "weighted_score": 23,
      "edge": 0.225,
      "confidence": 23,
      "prime_strength": 54,
      "P_chosen": 0.588
    },
    {
      "symbol": "DOGEUSDT",
      "side": "long",
      "weighted_score": 22,
      "edge": 0.224,
      "confidence": 22,
      "prime_strength": 55,
      "P_chosen": 0.595
    },
    {
      "symbol": "SOLUSDT",
      "side": "long",
      "weighted_score": 20,
      "edge": 0.198,
      "confidence": 20,
      "prime_strength": 54,
      "P_chosen": 0.642
    },
    {
      "symbol": "XRPUSDT",
      "side": "long",
      "weighted_score": 18,
      "edge": 0.18,
      "confidence": 18,
      "prime_strength": 52,
      "P_chosen": 0.597
    },
    {
      "symbol": "STRKUSDT",
      "side": "long",
      "weighted_score": 16,
      "edge": 0.159,
      "confidence": 16,
      "prime_strength": 47,
      "P_chosen": 0.568
    },
    {
      "symbol": "WLFIUSDT",
      "side": "long",
      "weighted_score": 14,
      "edge": 0.144,
      "confidence": 14,
      "prime_strength": 46,
      "P_chosen": 0.569
    },
    {
      "symbol": "ETHUSDT",
      "side": "long",
      "weighted_score": 11,
      "edge": 0.109,
      "confidence": 11,
      "prime_strength": 41,
      "P_chosen": 0.546
    },
    {
      "symbol": "LTCUSDT",
      "side": "long",
      "weighted_score": 8,
      "edge": 0.081,
      "confidence": 8,
      "prime_strength": 37,
      "P_chosen": 0.532
    },
    {
      "symbol": "ASTERUSDT",
      "side": "long",
      "weighted_score": 7,
      "edge": 0.074,
      "confidence": 7,
      "prime_strength": 36,
      "P_chosen": 0.529
    }
  ],
  "rejection_reasons": {
    "❌ Prime强度不足": 9,
    "❌ 概率过低": 7,
    "❌ 置信度不足": 8,
    "❌ Edge不足": 9
  },
  "close_to_threshold": [],
  "market_stats": {
    "avg_edge": 0.11,
    "avg_confidence": 10.9,
    "new_coins_count": 0,
    "new_coins_pct": 0.0
  },
  "factor_distribution": {
    "T": {
      "min": -40,
      "p25": -19.0,
      "median": 9.0,
      "p75": 36.0,
      "max": 96
    },
    "M": {
      "min": -48,
      "p25": -23.0,
      "median": -1.0,
      "p75": 14.0,
      "max": 42
    },
    "C": {
      "min": -17,
      "p25": -12.0,
      "median": 9.0,
      "p75": 16.0,
      "max": 49
    },
    "V": {
      "min": -44,
      "p25": 5.0,
      "median": 14.0,
      "p75": 24.0,
      "max": 47
    },
    "O": {
      "min": -43,
      "p25": -20.0,
      "median": -13.0,
      "p75": 3.0,
      "max": 48
    },
    "B": {
      "min": -95,
      "p25": -40.0,
      "median": -16.0,
      "p75": 0.0,
      "max": 6
    },
    "F": {
      "min": -29,
      "p25": -8.0,
      "median": 0.0,
      "p75": 2.0,
      "max": 35
    },
    "L": {
      "min": 48,
      "p25": 87.0,
      "median": 100.0,
      "p75": 100.0,
      "max": 100
    },
    "S": {
      "min": -100,
      "p25": -77.0,
      "median": 60.0,
      "p75": 82.0,
      "max": 99
    },
    "I": {
      "min": -96,
      "p25": -55.0,
      "median": -29.0,
      "p75": -20.0,
      "max": 0
    }
  },
  "factor_anomalies": {
    "F_saturation": {
      "count": 0,
      "pct": 0.0,
      "coins": []
    },
    "I_default": {
      "count": 0,
      "pct": 0.0,
      "coins": []
    },
    "F_meta_summary": {
      "F_raw": {
        "min": -0.1472,
        "mean": -0.0034,
        "median": 0.0017,
        "max": 0.185,
        "count": 19
      },
      "fund_momentum": {
        "min": -0.1849,
        "mean": -0.0229,
        "median": -0.0126,
        "max": 0.1017,
        "count": 19
      },
      "price_momentum": {
        "min": -0.2958,
        "mean": -0.0195,
        "median": 0.0004,
        "max": 0.1092,
        "count": 19
      }
    },
    "I_meta_summary": {
      "beta_btc": {
        "min": -3.9407,
        "mean": 1.6543,
        "median": 0.8762,
        "max": 8.429,
        "count": 19
      },
      "beta_eth": {
        "min": -5.4463,
        "mean": 0.5141,
        "median": 0.6415,
        "max": 9.3664,
        "count": 19
      }
    }
  },
  "threshold_recommendations": [],
  "performance": {
    "total_time_sec": 3.0,
    "speed_coins_per_sec": 6.67,
    "api_calls": 0,
    "cache_hit_rate": "100.0%",
    "memory_mb": 81.11953735351562
  }
}